README.md
easytimer.py
setup.py
easytimer.egg-info/PKG-INFO
easytimer.egg-info/SOURCES.txt
easytimer.egg-info/dependency_links.txt
easytimer.egg-info/top_level.txt