Metadata-Version: 2.1
Name: easytimer
Version: 0.3
Summary: A module for easily timing sections of code.
Home-page: UNKNOWN
Author: Adam Rose
License: UNKNOWN
Platform: UNKNOWN
Classifier: Programming Language :: Python :: 3
